LICENSE
MANIFEST.in
README.md
install-requirements.txt
setup.py
heptapod/VERSION
heptapod/__init__.py
heptapod/clone_bundles.py
heptapod/heptapod.example.hgrc
heptapod/hgrc.py
heptapod/obsutil.py
heptapod/patch.py
heptapod/required.hgrc
heptapod/util.py
heptapod/wsgi.py
heptapod.egg-info/PKG-INFO
heptapod.egg-info/SOURCES.txt
heptapod.egg-info/dependency_links.txt
heptapod.egg-info/requires.txt
heptapod.egg-info/top_level.txt
heptapod/gitlab/__init__.py
heptapod/gitlab/branch.py
heptapod/gitlab/change.py
heptapod/gitlab/hooks.py
heptapod/gitlab/prune_reasons.py
heptapod/gitlab/tag.py
heptapod/gitlab/tests/__init__.py
heptapod/gitlab/tests/test_change.py
heptapod/gitlab/tests/test_hooks_inner.py
heptapod/gitlab/tests/test_hooks_integration.py
heptapod/hooks/__init__.py
heptapod/hooks/check_publish.py
heptapod/hooks/dev_util.py
heptapod/hooks/gitlab_mirror.py
heptapod/hooks/perm.py
heptapod/hooks/subrepos.py
heptapod/hooks/tests/__init__.py
heptapod/hooks/tests/test_check_publish.py
heptapod/hooks/tests/test_check_write.py
heptapod/hooks/tests/test_dev_utils.py
heptapod/hooks/tests/test_gitlab_mirror.py
heptapod/hooks/tests/utils.py
heptapod/testhelpers/__init__.py
heptapod/testhelpers/git.py
heptapod/testhelpers/gitlab.py
heptapod/testhelpers/hg.py
heptapod/testhelpers/tests/__init__.py
heptapod/testhelpers/tests/test_git.py
heptapod/testhelpers/tests/test_gitlab.py
heptapod/testhelpers/tests/test_repo_wrapper.py
heptapod/tests/__init__.py
heptapod/tests/test_harness.py
heptapod/tests/test_hgrc.py
heptapod/tests/test_package.py
heptapod/tests/test_patch.py
heptapod/tests/test_util.py
heptapod/tests/test_wsgi.py
heptapod/tests/test_wsgi_webtest.py
hgext3rd/__init__.py
hgext3rd/heptapod/__init__.py
hgext3rd/heptapod/branch.py
hgext3rd/heptapod/git.py
hgext3rd/heptapod/keep_around.py
hgext3rd/heptapod/no_git.py
hgext3rd/heptapod/special_ref.py
hgext3rd/heptapod/state_maintainer.py
hgext3rd/heptapod/tag.py
hgext3rd/heptapod/topic.py
hgext3rd/heptapod/typed_ref.py
hgext3rd/heptapod/tests/__init__.py
hgext3rd/heptapod/tests/test_backups.py
hgext3rd/heptapod/tests/test_commands_misc.py
hgext3rd/heptapod/tests/test_config.py
