Metadata-Version: 2.1
Name: heptapod
Version: 5.2.1
Summary: Heptapod server-side Mercurial hooks, extension, etc.
Home-page: https://foss.heptapod.net/heptapod/py-heptapod
Author: Georges Racinet
Author-email: georges.racinet@octobus.net
License: GPLv2+
Keywords: hg mercurial heptapod gitlab
Classifier: Development Status :: 4 - Beta
Classifier: License :: OSI Approved :: GNU General Public License v2 or later (GPLv2+)
Classifier: Programming Language :: Python :: 2.7
Classifier: Programming Language :: Python :: 2 :: Only
Classifier: Topic :: Software Development :: Version Control :: Mercurial
License-File: LICENSE
Requires-Dist: Mercurial>=6.1
Requires-Dist: hg-evolve<11.2,>=11.0.1
Requires-Dist: hg-git~=1.1.0
Requires-Dist: hg-loggingmod>=0.2.1
Requires-Dist: hg-configexpress~=0.4.0
Requires-Dist: dulwich<0.22
Requires-Dist: requests==2.31.0
Requires-Dist: requests_unixsocket==0.2.0
Requires-Dist: urllib3<2
Requires-Dist: attrs~=23.2.0
Requires-Dist: python_jwt~=4.0.0
Requires-Dist: boto3~=1.35.99
